{
  "type": "pfm:furniture",
  "group": "bedroom",
  "ingredients": [
    {
      "item": "biomeswevegone:witch_hazel_planks"
    },
    {
      "item": "biomeswevegone:witch_hazel_planks"
    },
    {
      "item": "biomeswevegone:witch_hazel_planks"
    },
    {
      "item": "biomeswevegone:witch_hazel_planks"
    },
    {
      "item": "biomeswevegone:witch_hazel_planks"
    },
    {
      "item": "minecraft:light_blue_bed"
    }
  ],
  "result": {
    "item": "pfm:witch_hazel_biomeswevegone_light_blue_simple_bed"
  }
}